aiweb/__init__.py
aiweb/app.py
aiweb/config.py
aiweb/utils/__init__.py
aiweb/utils/ai_path.py
aiweb/utils/ai_tools.py
aiweb/utils/ai_wraper.py
ai_web-0.0.3.dist-info/LICENSE
ai_web-0.0.3.dist-info/METADATA
ai_web-0.0.3.dist-info/WHEEL
ai_web-0.0.3.dist-info/top_level.txt
ai_web-0.0.3.dist-info/RECORD
