Metadata-Version: 2.1
Name: ai-web
Version: 0.0.3
Summary: AI自动生成接口
Home-page: https://github.com/CLANNADHH/ai_web
Author: clannadhh
Maintainer: clannadhh
License: MIT Licence
Keywords: pip
Platform: any
Classifier: Development Status :: 4 - Beta
Classifier: Intended Audience :: Developers
Classifier: License :: OSI Approved :: Apache Software License
Classifier: Programming Language :: Python :: 3.5
Classifier: Programming Language :: Python :: 3.6
Classifier: Topic :: Software Development :: Libraries
Requires-Dist: klein
Requires-Dist: numpy
